{
	"info": {
		"_postman_id": "be1169c3-29ca-4000-931e-06e8176a4153",
		"name": "Youtube",
		"schema": "https://schema.getpostman.com/json/collection/v2.1.0/collection.json"
	},
	"item": [
		{
			"name": "Using Graphql For Microservice Communication",
			"item": [
				{
					"name": "Get Post By User Id",
					"request": {
						"method": "GET",
						"header": [],
						"url": {
							"raw": "http://localhost:8082/get/posts/user/2",
							"protocol": "http",
							"host": [
								"localhost"
							],
							"port": "8082",
							"path": [
								"get",
								"posts",
								"user",
								"2"
							]
						}
					},
					"response": []
				},
				{
					"name": "List Posts",
					"request": {
						"method": "GET",
						"header": [],
						"url": {
							"raw": "http://localhost:8082/list/posts",
							"protocol": "http",
							"host": [
								"localhost"
							],
							"port": "8082",
							"path": [
								"list",
								"posts"
							]
						}
					},
					"response": []
				},
				{
					"name": "Get Post By Id",
					"request": {
						"method": "GET",
						"header": [],
						"url": {
							"raw": "http://localhost:8082/get/posts/5",
							"protocol": "http",
							"host": [
								"localhost"
							],
							"port": "8082",
							"path": [
								"get",
								"posts",
								"5"
							]
						}
					},
					"response": []
				},
				{
					"name": "List Users",
					"request": {
						"method": "GET",
						"header": [],
						"url": {
							"raw": "http://localhost:8081/list/users",
							"protocol": "http",
							"host": [
								"localhost"
							],
							"port": "8081",
							"path": [
								"list",
								"users"
							]
						}
					},
					"response": []
				},
				{
					"name": "Get User By Id",
					"request": {
						"method": "GET",
						"header": [],
						"url": {
							"raw": "http://localhost:8081/get/users/1",
							"protocol": "http",
							"host": [
								"localhost"
							],
							"port": "8081",
							"path": [
								"get",
								"users",
								"1"
							]
						}
					},
					"response": []
				}
			]
		}
	]
}